ansible_galaxy/__init__.py
ansible_galaxy/archive.py
ansible_galaxy/build.py
ansible_galaxy/collection_artifact.py
ansible_galaxy/collection_artifact_file_manifest.py
ansible_galaxy/collection_artifact_manifest.py
ansible_galaxy/collection_info.py
ansible_galaxy/collection_members.py
ansible_galaxy/collections_lockfile.py
ansible_galaxy/dependencies.py
ansible_galaxy/display.py
ansible_galaxy/download.py
ansible_galaxy/galaxy_repository_spec.py
ansible_galaxy/install.py
ansible_galaxy/install_info.py
ansible_galaxy/installed_content_item_db.py
ansible_galaxy/installed_namespaces_db.py
ansible_galaxy/installed_repository_db.py
ansible_galaxy/matchers.py
ansible_galaxy/mazer_version.py
ansible_galaxy/multipart_form.py
ansible_galaxy/repository.py
ansible_galaxy/repository_archive.py
ansible_galaxy/repository_spec.py
ansible_galaxy/repository_spec_parse.py
ansible_galaxy/repository_version.py
ansible_galaxy/requirements.py
ansible_galaxy/rest_api.py
ansible_galaxy/role_metadata.py
ansible_galaxy/user_agent.py
ansible_galaxy/yaml_persist.py
ansible_galaxy/actions/__init__.py
ansible_galaxy/actions/build.py
ansible_galaxy/actions/info.py
ansible_galaxy/actions/install.py
ansible_galaxy/actions/list.py
ansible_galaxy/actions/migrate_role.py
ansible_galaxy/actions/publish.py
ansible_galaxy/actions/remove.py
ansible_galaxy/actions/version.py
ansible_galaxy/compat/__init__.py
ansible_galaxy/config/__init__.py
ansible_galaxy/config/config.py
ansible_galaxy/config/config_file.py
ansible_galaxy/config/defaults.py
ansible_galaxy/config/yaml_file.py
ansible_galaxy/data/__init__.py
ansible_galaxy/data/spdx_licenses.json
ansible_galaxy/data/spdx_licenses.py
ansible_galaxy/exceptions/__init__.py
ansible_galaxy/fetch/__init__.py
ansible_galaxy/fetch/base.py
ansible_galaxy/fetch/editable.py
ansible_galaxy/fetch/fetch_factory.py
ansible_galaxy/fetch/galaxy_url.py
ansible_galaxy/fetch/local_file.py
ansible_galaxy/fetch/remote_url.py
ansible_galaxy/fetch/scm_url.py
mazer-1.0.0.dist-info/AUTHORS.rst
mazer-1.0.0.dist-info/LICENSE
mazer-1.0.0.dist-info/METADATA
mazer-1.0.0.dist-info/WHEEL
mazer-1.0.0.dist-info/entry_points.txt
mazer-1.0.0.dist-info/top_level.txt
mazer-1.0.0.dist-info/RECORD
