Metadata-Version: 2.1
Name: mazer
Version: 1.0.0
Summary: Ansible content manager
Home-page: https://github.com/ansible/galaxy-cli
Author: Red Hat, Inc.
Author-email: info@ansible.com
License: GPLv3
Keywords: mazer
Platform: UNKNOWN
Classifier: Development Status :: 2 - Pre-Alpha
Classifier: Intended Audience :: Developers
Classifier: License :: OSI Approved :: Apache Software License
Classifier: Natural Language :: English
Classifier: Programming Language :: Python :: 2
Classifier: Programming Language :: Python :: 2.6
Classifier: Programming Language :: Python :: 2.7
Classifier: Programming Language :: Python :: 3
Classifier: Programming Language :: Python :: 3.6
